msgraph/__init__.py
msgraph2/__init__.py
msgraph2-0.4.dist-info/LICENSE
msgraph2-0.4.dist-info/METADATA
msgraph2-0.4.dist-info/WHEEL
msgraph2-0.4.dist-info/top_level.txt
msgraph2-0.4.dist-info/RECORD
