Metadata-Version: 2.1
Name: msgraph2
Version: 0.4
Summary: A Pythonic interface to Microsoft's Graph API
Author: jhunt
License: The MIT License (MIT)
Project-URL: Documentation, https://github.com/jhunt/msgraph2/blob/main/README.md
Project-URL: Issues, https://github.com/jhunt/msgraph2/issues
Project-URL: Source, https://github.com/jhunt/msgraph2
Classifier: Programming Language :: Python :: 3.9
Classifier: License :: OSI Approved :: MIT License
Classifier: Operating System :: OS Independent
Requires-Python: >=3.9
License-File: LICENSE
Requires-Dist: requests
